<?xml version="1.0" encoding="utf-8"?>
<Player xmlns:xsd="http://www.w3.org/2001/XMLSchema" xmlns:xsi="http://www.w3.org/2001/XMLSchema-instance">
  <level>1</level>
  <followers>1000</followers>
  <money>50</money>
  <pension>10</pension>
  <experience>0</experience>
  <x>301.26358</x>
  <y>18.28453</y>
  <z>109.056068</z>
  <inventory>
    <items>
      <InventoryItem>
        <ID>9c628946-321b-410f-8826-374a61318f5f</ID>
        <tag>CROCC01</tag>
        <numUses>0</numUses>
      </InventoryItem>
      <InventoryItem>
        <ID>9c628946-321b-410f-8826-374a61318f6f</ID>
        <tag>DIV01</tag>
        <numUses>0</numUses>
      </InventoryItem>
    </items>
  </inventory>
</Player>