<?xml version="1.0" encoding="utf-8"?>
<ArrayOfKeyItem xmlns:xsd="http://www.w3.org/2001/XMLSchema" xmlns:xsi="http://www.w3.org/2001/XMLSchema-instance">

    <KeyItem>
        <tag>KEY001</tag>
        <name>Giravite</name>
        <descrizione>Immancabile strumento di Zio Agosto</descrizione>
        <durability>100</durability>
        <imagePath>giravite</imagePath>
    </KeyItem>
    <KeyItem>
        <tag>KEY002</tag>
        <name>Pozione Rara</name>
        <descrizione>Immancabile strumento di Zio Agosto per curare i polli</descrizione>
        <durability>100</durability>
        <imagePath>pozione</imagePath>
    </KeyItem>
    <KeyItem>
        <tag>KEY003</tag>
        <name>Zappa</name>
        <descrizione>Strumento per curare l'orto</descrizione>
        <durability>50</durability>
        <imagePath>zappa</imagePath>
    </KeyItem>
    <KeyItem>
        <tag>MASCHERA001</tag>
        <name>Maschera protettiva</name>
        <descrizione>Maschera protettiva per zio Agosto</descrizione>
        <durability>10</durability>
        <imagePath>mask</imagePath>
    </KeyItem>
    <KeyItem>
        <tag>KEY005</tag>
        <name>Tenaglia</name>
        <descrizione>Chiave per aprire la porta</descrizione>
        <durability>10</durability>
        <imagePath>tenaglia</imagePath>
    </KeyItem>
    <KeyItem>
        <tag>KEY006</tag>
        <name>Sega</name>
        <descrizione>Chiave per aprire la porta</descrizione>
        <durability>27</durability>
        <imagePath>sega</imagePath>
    </KeyItem>

    <KeyItem>
        <tag>MISS01A</tag>
        <name>Faro destro</name>
        <descrizione>Faro destro</descrizione>
        <durability>1</durability>
        <imagePath>giravite</imagePath>
    </KeyItem>
    <KeyItem>
        <tag>MISS01B</tag>
        <name>Faro sinistro</name>
        <descrizione>Faro sinistro</descrizione>
        <durability>1</durability>
        <imagePath>giravite</imagePath>
    </KeyItem>
    <KeyItem>
        <tag>MISS01C</tag>
        <name>Faro centrale</name>
        <descrizione>Faro centrale</descrizione>
        <durability>1</durability>
        <imagePath>giravite</imagePath>
    </KeyItem>

</ArrayOfKeyItem>
