<?xml version="1.0" encoding="utf-8"?>
<SavedStats xmlns:xsd="http://www.w3.org/2001/XMLSchema" xmlns:xsi="http://www.w3.org/2001/XMLSchema-instance">
  <day>3</day>
  <update_cat_timer>3181.513</update_cat_timer>
  <interaction_cat_timer>9.203262</interaction_cat_timer>
  <interactions_cat>358</interactions_cat>
  <day_timer>47483</day_timer>
  <timestamp_seconds>3129</timestamp_seconds>
  <dayTime>AFTERNOON</dayTime>
  <videoStatus>DONE</videoStatus>
  <sleepStatus>AVAILABLE</sleepStatus>
</SavedStats>